install/__init__.py
install/test.py
install/versioning.py
tfopgen/__init__.py
tfopgen/create_op.py
tfopgen/util.py
tfopgen/version.py
tfopgen/bin/tfopgen
tfopgen/examples/complex_phase.yml
tfopgen/examples/simple.yml
tfopgen/templates/Makefile.j2
tfopgen/templates/cpp_header.j2
tfopgen/templates/cpp_source.j2
tfopgen/templates/cuda_header.j2
tfopgen/templates/cuda_source.j2
tfopgen/templates/main_header.j2
tfopgen/templates/test_source.j2
tfopgen-0.2.4.data/scripts/tfopgen
tfopgen-0.2.4.dist-info/DESCRIPTION.rst
tfopgen-0.2.4.dist-info/LICENSE.txt
tfopgen-0.2.4.dist-info/METADATA
tfopgen-0.2.4.dist-info/RECORD
tfopgen-0.2.4.dist-info/WHEEL
tfopgen-0.2.4.dist-info/metadata.json
tfopgen-0.2.4.dist-info/top_level.txt
tfopgen-0.2.4.dist-info/zip-safe
