Metadata-Version: 2.0
Name: tfopgen
Version: 0.2.4
Summary: Generates tensorflow custom operator boilerplate
Home-page: UNKNOWN
Author: Simon Perkins
Author-email: simon.perkins@gmail.com
License: UNKNOWN
Platform: UNKNOWN
Classifier: Development Status :: 3 - Alpha
Classifier: Intended Audience :: Developers
Classifier: License :: OSI Approved :: MIT License
Classifier: Operating System :: OS Independent
Classifier: Programming Language :: Python
Classifier: Topic :: Software Development :: Libraries :: Python Modules
Requires-Dist: jinja2 (>=2.8.0)
Requires-Dist: numpy (>=1.12.0)
Requires-Dist: ruamel.yaml (>=0.13.7)
